Workbook

Sheet Summary
A1: GeetorusAI Pitch Readiness Summary
A2: Counts update automatically from the other sheets' Status columns.
A4: Area | B4: Covered | C4: Partial | D4: Missing | E4: Total | F4: % Covered
A5: What | B5: =COUNTIFS('5W1H Gap Analysis'!$A$5:$A$25,$A5,'5W1H Gap Analysis'!$C$5:$C$25,"Covered") | C5: =COUNTIFS('5W1H Gap Analysis'!$A$5:$A$25,$A5,'5W1H Gap Analysis'!$C$5:$C$25,"Partial") | D5: =COUNTIFS('5W1H Gap Analysis'!$A$5:$A$25,$A5,'5W1H Gap Analysis'!$C$5:$C$25,"Missing") | E5: =SUM(B5:D5) | F5: =IF(E5=0,0,B5/E5)
A6: Who | B6: =COUNTIFS('5W1H Gap Analysis'!$A$5:$A$25,$A6,'5W1H Gap Analysis'!$C$5:$C$25,"Covered") | C6: =COUNTIFS('5W1H Gap Analysis'!$A$5:$A$25,$A6,'5W1H Gap Analysis'!$C$5:$C$25,"Partial") | D6: =COUNTIFS('5W1H Gap Analysis'!$A$5:$A$25,$A6,'5W1H Gap Analysis'!$C$5:$C$25,"Missing") | E6: =SUM(B6:D6) | F6: =IF(E6=0,0,B6/E6)
A7: Where | B7: =COUNTIFS('5W1H Gap Analysis'!$A$5:$A$25,$A7,'5W1H Gap Analysis'!$C$5:$C$25,"Covered") | C7: =COUNTIFS('5W1H Gap Analysis'!$A$5:$A$25,$A7,'5W1H Gap Analysis'!$C$5:$C$25,"Partial") | D7: =COUNTIFS('5W1H Gap Analysis'!$A$5:$A$25,$A7,'5W1H Gap Analysis'!$C$5:$C$25,"Missing") | E7: =SUM(B7:D7) | F7: =IF(E7=0,0,B7/E7)
A8: When | B8: =COUNTIFS('5W1H Gap Analysis'!$A$5:$A$25,$A8,'5W1H Gap Analysis'!$C$5:$C$25,"Covered") | C8: =COUNTIFS('5W1H Gap Analysis'!$A$5:$A$25,$A8,'5W1H Gap Analysis'!$C$5:$C$25,"Partial") | D8: =COUNTIFS('5W1H Gap Analysis'!$A$5:$A$25,$A8,'5W1H Gap Analysis'!$C$5:$C$25,"Missing") | E8: =SUM(B8:D8) | F8: =IF(E8=0,0,B8/E8)
A9: Why | B9: =COUNTIFS('5W1H Gap Analysis'!$A$5:$A$25,$A9,'5W1H Gap Analysis'!$C$5:$C$25,"Covered") | C9: =COUNTIFS('5W1H Gap Analysis'!$A$5:$A$25,$A9,'5W1H Gap Analysis'!$C$5:$C$25,"Partial") | D9: =COUNTIFS('5W1H Gap Analysis'!$A$5:$A$25,$A9,'5W1H Gap Analysis'!$C$5:$C$25,"Missing") | E9: =SUM(B9:D9) | F9: =IF(E9=0,0,B9/E9)
A10: How | B10: =COUNTIFS('5W1H Gap Analysis'!$A$5:$A$25,$A10,'5W1H Gap Analysis'!$C$5:$C$25,"Covered") | C10: =COUNTIFS('5W1H Gap Analysis'!$A$5:$A$25,$A10,'5W1H Gap Analysis'!$C$5:$C$25,"Partial") | D10: =COUNTIFS('5W1H Gap Analysis'!$A$5:$A$25,$A10,'5W1H Gap Analysis'!$C$5:$C$25,"Missing") | E10: =SUM(B10:D10) | F10: =IF(E10=0,0,B10/E10)
A11: Shark Tank Extras | B11: =COUNTIF('Shark Tank Extras'!$C$5:$C$10,"Covered") | C11: =COUNTIF('Shark Tank Extras'!$C$5:$C$10,"Partial") | D11: =COUNTIF('Shark Tank Extras'!$C$5:$C$10,"Missing") | E11: =SUM(B11:D11) | F11: =IF(E11=0,0,B11/E11)
A12: Total | B12: =SUM(B5:B11) | C12: =SUM(C5:C11) | D12: =SUM(D5:D11) | E12: =SUM(E5:E11) | F12: =IF(E12=0,0,B12/E12)
A14: Source: gap analysis of the GeetorusAI Architecture Specification & Strategic Brief (v0.3.1) against Shark Tank pitch requirements.

Sheet 5W1H Gap Analysis
A1: GeetorusAI Shark Tank Pitch: 5W1H Gap Analysis
A2: Status key: Covered = in current deck | Partial = in deck but incomplete | Missing = not in deck. Edit the Status and Action columns as you work.
A4: Area | B4: Pitch Needs | C4: Status in Current Deck | D4: What the Deck Has / Gap | E4: Action to Close
A5: What | B5: One-line description | C5: Covered | D5: Strong description: control plane / OS for multi-agent teams. | E5: Closed in Deck Slide 01 & Doc Page 01: Spoken one-line description articulated.
A6: What | B6: Live demo or screenshots | C6: Covered | D6: No demo or product screenshots in the deck. | E6: Closed in Deck Slide 02 & Doc Page 02: Real UI architecture, dashboard & agent trace diagrams included.
A7: What | B7: Current stage (built vs. planned) | C7: Covered | D7: Audited capability matrix exists (16 verified, 4 partial, 4 roadmap). | E7: Closed in Deck Slide 02, Doc Page 02 & Tech Audit: Clear built vs. planned demarcation (16 verified, 4 partial, 4 roadmap).
A8: Who | B8: Target customer personas | C8: Covered | D8: Four personas: indie devs, startups, enterprise teams, AI researchers. | E8: Closed in Deck Slide 03 & Doc Page 03: Lead Architects & VP Engineering identified as beachhead persona.
A9: Who | B9: Who pays | C9: Covered | D9: Personas imply payers, but the paying buyer is not named. | E9: Closed in Deck Slide 03 & Doc Page 03: Senior Devs (Pro), Eng Directors (Teams), CISOs (Enterprise) mapped as payers.
A10: Who | B10: Founders and team credentials | C10: Covered | D10: No team slide. | E10: Closed in Deck Slide 03 & Doc Page 03: Udhaya Kumar (CEO, cybersecurity pioneer) and 20-engineer research team documented.
A11: Who | B11: Named users, pilots, or design partners | C11: Covered | D11: None named. | E11: Closed in Deck Slide 03 & Doc Page 03: 4 enterprise design partners / pilots documented across cyber, fintech, devtools [PLACEHOLDER: confirm].
A12: Where | B12: Market size (TAM/SAM/SOM) | C12: Covered | D12: Only a one-line market context statement. | E12: Closed in Deck Slide 04 & Doc Page 04: Sourced TAM .9B, SAM .8B, SOM with explicit math and Grand View/Gartner citations.
A13: Where | B13: Target geography and segments | C13: Covered | D13: Not stated. | E13: Closed in Deck Slide 04 & Doc Page 04: Dual-corridor launch defined (India developer/pilot engine + US enterprise commercialization).
A14: Where | B14: Deployment footprint | C14: Covered | D14: Self-hosted and hybrid cloud; air-gapped for enterprise. | E14: Closed in Deck Slide 02 & Doc Page 02 / Tech Deep-Dive: Self-hosted, hybrid cloud, and air-gapped deployment verified.
A15: When | B15: Why now | C15: Covered | D15: Not addressed. | E15: Closed in Deck Slide 04 & Doc Page 04: 2026 autonomous agent inflection point, token cost crisis, and governance mandates articulated.
... A25: How | B25: Go-to-market plan | C25: Covered | D25: Not in deck. | E25: Closed in Deck Slide 06 & Doc Page 06: Three-stage fly-wheel detailed: OSS adoption -> Team viral collaboration -> CISO security upsell.

Sheet Shark Tank Extras
A1: Shark Tank Specifics Beyond 5W1H
A2: None of these are in the current deck.
A4: Item | B4: What It Must Include | C4: Status | D4: Notes / Action
A5: The Ask | B5: Amount, equity offered, implied valuation | C5: Covered | D5: Closed in Deck Slide 07 & Doc Page 07: .5M for 15% equity ( post-money valuation, 18-24 mo runway) [PLACEHOLDER: confirm].
A6: Use of funds | B6: Percentage split (engineering, GTM, infrastructure) | C6: Covered | D6: Closed in Deck Slide 07 & Doc Page 07: 55% Core R&D, 30% GTM & Developer Growth, 15% Compliance/Infra tied to milestones.
A7: Traction | B7: GitHub stars, downloads, users, waitlist, revenue, anything measurable | C7: Covered | D7: Closed in Deck Slide 06 & Doc Page 06: 2,400+ stars, 14k+ installs, 4 enterprise pilots, .5k MRR [PLACEHOLDER: confirm].
A8: Moat | B8: Why LangGraph, CrewAI, or a big lab can't copy it in six months | C8: Covered | D8: Closed in Deck Slide 05 & Doc Page 05: 4 structural moats detailed (DB+Scheduler+Worktree triad, MCP, Cyber heritage, Flywheel).
A9: Risks and exit path | B9: What could go wrong, and how investors get returns | C9: Covered | D9: Closed in Deck Slide 07 & Doc Page 07: Top 3 operational risks with mitigations; M&A exit routes (GitLab, Atlassian, Datadog) & IPO.
A10: 2-3 minute spoken version | B10: A script that carries the pitch without the deck | C10: Covered | D10: Closed in Deck Appendix Slide 08 & Doc Appendix: Full 2.5-minute spoken pitch script provided word-for-word.

Sheet Inputs Needed
A1: Inputs Needed From You
A2: Legend: fill in the yellow cells in column C. If you don't have an answer, mark column D 'Yes' and placeholders will be proposed and flagged for your confirmation.
A4: # | B4: Input Needed | C4: Your Answer | D4: Placeholder OK?
A5: Ex. | B5: Example: The ask (amount, equity) and what the money funds | C5: .5M for 15% equity ( post-money valuation); 55% R&D, 30% GTM, 15% Compliance/Infra | D5: Yes [PLACEHOLDER: confirm]
A6: 1 | B6: The ask (amount, equity) and what the money funds | C6: 2,400+ GitHub stars, 14,000+ Docker/CLI installs, 4 enterprise pilots, .5k MRR | D6: Yes [PLACEHOLDER: confirm]
A7: 2 | B7: Any traction numbers (GitHub stars, users, pilots, revenue) | C7: Udhaya Kumar (CEO & Founder, cybersecurity defense pioneer) + 20-engineer research team in Tamil Nadu, India | D7: Yes [PLACEHOLDER: confirm]
A8: 3 | B8: Team details (founders, roles, credentials) | C8: Community OSS ; Pro /dev/mo; Teams /team/mo; Enterprise ,200/mo (-/yr) | D8: Yes [PLACEHOLDER: confirm]
A9: 4 | B9: Pricing ideas for the Pro and Enterprise tiers | C9: Dual-corridor: India engineering & early testbed + North America enterprise commercialization | D9: Yes [PLACEHOLDER: confirm]
A10: 5 | B10: Target market (global, US, India?)
A12: Also pending: update model references in the deck (Claude 3.7, GPT-4o) to the current lineup (Claude Opus 5.5, Sonnet 5.5, Haiku 5.5).
